georgesngandeu_hello/__init__.py
georgesngandeu_hello/hello1.py
georgesngandeu_hello/hello2.py
georgesngandeu_hello-0.0.2.dist-info/LICENSE
georgesngandeu_hello-0.0.2.dist-info/METADATA
georgesngandeu_hello-0.0.2.dist-info/WHEEL
georgesngandeu_hello-0.0.2.dist-info/top_level.txt
georgesngandeu_hello-0.0.2.dist-info/RECORD
