Metadata-Version: 2.1
Name: georgesngandeu-hello
Version: 0.0.2
Summary: A simple package that prints hello wolrd
Home-page: https://github.com/Georges-Ngandeu/HelloPython
Author: Georges Ngandeu
Author-email: georgesngandeu@gmail.com
License: Apache License 2.0
Platform: UNKNOWN
Classifier: Programming Language :: Python :: 3
Classifier: License :: OSI Approved :: MIT License
Classifier: Operating System :: OS Independent
